{
  "DisplayName": "Main",
  "Tooltip": null,
  "HelpLink": null,
  "Color": null,
  "OriginalIconFileName": null,
  "Arguments": [
    {
      "Name": "arrayDay",
      "DisplayName": "arrayDay",
      "Category": null,
      "Tooltip": null,
      "Placeholder": " 2024",
      "Widget": null,
      "IsRequired": false,
      "IsPrincipal": true,
      "ArgumentType": 0,
      "DataSourceItems": null
    },
    {
      "Name": "webMonth",
      "DisplayName": "webMonth",
      "Category": null,
      "Tooltip": null,
      "Placeholder": null,
      "Widget": null,
      "IsRequired": false,
      "IsPrincipal": true,
      "ArgumentType": 0,
      "DataSourceItems": null
    },
    {
      "Name": "webYear",
      "DisplayName": "webYear",
      "Category": null,
      "Tooltip": null,
      "Placeholder": null,
      "Widget": null,
      "IsRequired": false,
      "IsPrincipal": true,
      "ArgumentType": 0,
      "DataSourceItems": null
    },
    {
      "Name": "arrayDate",
      "DisplayName": "arrayDate",
      "Category": null,
      "Tooltip": null,
      "Placeholder": null,
      "Widget": null,
      "IsRequired": false,
      "IsPrincipal": true,
      "ArgumentType": 0,
      "DataSourceItems": null
    }
  ]
}